Metadata-Version: 2.1
Name: sentry-dingtalk-lz
Version: 1.0.0
Summary: A Sentry extension which integrates with Dinttalk robot.
Home-page: https://github.com/leonzhang2008/sentry-dingtalk.git
Author: leon zhang
Author-email: leonzhang2008@gmail.com
License: BSD
Platform: UNKNOWN
Classifier: Framework :: Django
Classifier: Intended Audience :: Developers
Classifier: Intended Audience :: System Administrators
Classifier: Operating System :: OS Independent
Classifier: Topic :: Software Development
Requires-Dist: sentry (>=5.4.1)
Provides-Extra: test
